authservice/__init__.py
authservice/api_client.py
authservice/api_response.py
authservice/configuration.py
authservice/exceptions.py
authservice/py.typed
authservice/rest.py
authservice/api/__init__.py
authservice/api/default_api.py
authservice/models/__init__.py
authservice/models/client_get200_response.py
authservice/models/client_get401_response.py
authservice/models/login_client_post200_response.py
authservice/models/login_client_post401_response.py
authservice/models/regenerate_client_credentials_post200_response.py
authservice/models/register_post201_response.py
authservice/models/register_post400_response.py
authservice/models/register_post500_response.py
authservice-0.0.2.dist-info/METADATA
authservice-0.0.2.dist-info/WHEEL
authservice-0.0.2.dist-info/top_level.txt
authservice-0.0.2.dist-info/RECORD
