Metadata-Version: 2.1
Name: authservice
Version: 0.0.2
Summary: With this SDK, Python developers can easily interact with the Auth API, enabling hassle-free implementation of user registration, login, and client credential management features within their applications.
Home-page: https://github.com/CodeCrew24/authservice_python
Author: Code Crew24
Author-email: dprakash2101@gmail.com
License: MIT
Project-URL: GitHub Repo, https://github.com/CodeCrew24/authservice_python
Project-URL: Download, https://github.com/CodeCrew24/authservice_python/archive/1.0.0.tar.gz
Project-URL: Release Notes, https://github.com/CodeCrew24/authservice_python/releases/
Keywords: token based auth,Bearer Token,Auth Service
Requires-Dist: urllib3 <2.1.0,>=1.25.3
Requires-Dist: python-dateutil
Requires-Dist: pydantic >=2
Requires-Dist: typing-extensions >=4.7.1
